dwd_global_radiation/__init__.py
dwd_global_radiation/global_radiation.py
dwd_global_radiation/global_radiation_printer.py
dwd_global_radiation/utils.py
dwd_global_radiation-1.1.0rc6.dist-info/LICENSE
dwd_global_radiation-1.1.0rc6.dist-info/METADATA
dwd_global_radiation-1.1.0rc6.dist-info/WHEEL
dwd_global_radiation-1.1.0rc6.dist-info/top_level.txt
dwd_global_radiation-1.1.0rc6.dist-info/RECORD
