Metadata-Version: 2.1
Name: dwd_global_radiation
Version: 1.1.0rc6
Summary: Access and analyze DWD global radiation data and forecasts
Home-page: https://github.com/aschmere/dwd_global_radiation
Author: Arno Schmerer
License: MIT
Keywords: weather meteorology radiation solar forecasting DWD data environmental data climate studies solar energy forecasting
Classifier: Development Status :: 4 - Beta
Classifier: Intended Audience :: Developers
Classifier: License :: OSI Approved :: MIT License
Classifier: Operating System :: OS Independent
Classifier: Programming Language :: Python :: 3
Classifier: Programming Language :: Python :: 3.12
Classifier: Topic :: Software Development :: Libraries
License-File: LICENSE
Requires-Dist: beautifulsoup4 >=4.12.3
Requires-Dist: netCDF4 >=1.6.5
Requires-Dist: numpy >=1.26.0
Requires-Dist: pytz >=2024.1
Requires-Dist: requests >=2.31.0
Requires-Dist: tabulate >=0.9.0
Requires-Dist: tzlocal >=5.2
Requires-Dist: xarray >=2024.3.0
